imstack/__init__.py
imstack/_modidx.py
imstack/_nbdev.py
imstack/core.py
imstack-0.1.8.dist-info/LICENSE
imstack-0.1.8.dist-info/METADATA
imstack-0.1.8.dist-info/WHEEL
imstack-0.1.8.dist-info/entry_points.txt
imstack-0.1.8.dist-info/top_level.txt
imstack-0.1.8.dist-info/RECORD
