Metadata-Version: 2.1
Name: imstack
Version: 0.1.8
Summary: Represent an image as a stack of different sized tensors
Home-page: https://github.com/johnowhitaker/imstack/tree/main/
Author: Jonathan Whitaker
Author-email: johnowhitaker@gmail.com
License: Apache Software License 2.0
Keywords: image
Platform: UNKNOWN
Classifier: Development Status :: 3 - Alpha
Classifier: Intended Audience :: Developers
Classifier: Natural Language :: English
Classifier: Programming Language :: Python :: 3.6
Classifier: Programming Language :: Python :: 3.7
Classifier: Programming Language :: Python :: 3.8
Classifier: Programming Language :: Python :: 3.9
Classifier: Programming Language :: Python :: 3.10
Classifier: License :: OSI Approved :: Apache Software License
Requires-Python: >=3.6
License-File: LICENSE
Requires-Dist: matplotlib
Requires-Dist: pillow
Requires-Dist: torch
Provides-Extra: dev
